LICENSE
MANIFEST.in
README.md
requirements.txt
setup.py
tox.ini
django_ssl_redirect.egg-info/PKG-INFO
django_ssl_redirect.egg-info/SOURCES.txt
django_ssl_redirect.egg-info/dependency_links.txt
django_ssl_redirect.egg-info/top_level.txt
ssl_redirect/__init__.py
ssl_redirect/middleware.py