Metadata-Version: 1.1
Name: django-ssl-redirect
Version: 2.1.1
Summary: A middleware that secures URLS.
Home-page: https://bitbucket.org/nextscreenlabs/django-ssl-redirect
Author: Jason Christa
Author-email: jason@zeitcode.com
License: UNKNOWN
Platform: UNKNOWN
Classifier: Environment :: Web Environment
Classifier: License :: OSI Approved :: BSD License
Classifier: Framework :: Django
Classifier: Programming Language :: Python
